uart/src/receiver.v
module receiver (
    input  wire       clk,
    input  wire       rst_n,
    input  wire       rx,
    output reg  [7:0] data_out,
    output reg        data_ready
);

    parameter integer CLK_FREQ = 24_000_000;
    parameter integer BAUD_RATE = 115200;

    localparam integer CYC_PER_BIT = CLK_FREQ / BAUD_RATE;
    localparam integer HALF_CYC_PER_BIT = CYC_PER_BIT / 2;

    reg [1:0] rx_sync;

    // Trying to reduce metastability
    always @(posedge clk or negedge rst_n) begin
        if (!rst_n) begin
            rx_sync <= 2'b11;
        end else begin
            rx_sync <= {rx_sync[0], rx};
        end
    end


    // Receiver state machine
    localparam [1:0] STATE_IDLE = 2'd0;
    localparam [1:0] STATE_START = 2'd1;
    localparam [1:0] STATE_DATA = 2'd2;
    localparam [1:0] STATE_STOP = 2'd3;

    reg [ 1:0] state;
    reg [ 2:0] bit_index;
    reg [15:0] clk_count;
    reg [ 7:0] rx_shift_reg;


    always @(posedge clk or negedge rst_n) begin
        if (!rst_n) begin
            state        <= STATE_IDLE;
            data_out     <= 8'd0;
            data_ready   <= 1'b0;
            bit_index    <= 3'd0;
            clk_count    <= 16'd0;
            rx_shift_reg <= 8'd0;
        end else begin
            data_ready <= 1'b0;

            case (state)
                STATE_IDLE: begin
                    clk_count <= 16'd0;
                    bit_index <= 3'd0;

                    if (rx_sync[1] == 1'b0) begin
                        state <= STATE_START;
                    end
                end

                STATE_START: begin
                    if (clk_count < HALF_CYC_PER_BIT - 1) begin
                        clk_count <= clk_count + 1'b1;
                    end else begin
                        if (rx_sync[1] == 1'b0) begin
                            clk_count <= 16'd0;
                            state     <= STATE_DATA;
                        end else begin
                            state <= STATE_IDLE;
                        end
                    end
                end

                STATE_DATA: begin
                    if (clk_count < CYC_PER_BIT - 1) begin
                        clk_count <= clk_count + 1'b1;
                    end else begin
                        clk_count               <= 16'd0;
                        rx_shift_reg[bit_index] <= rx_sync[1];
                        if (bit_index < 3'd7) begin
                            bit_index <= bit_index + 1'b1;
                        end else begin
                            bit_index <= 3'd0;
                            state     <= STATE_STOP;
                        end
                    end
                end

                STATE_STOP: begin
                    if (clk_count < CYC_PER_BIT - 1) begin
                        clk_count <= clk_count + 1'b1;
                    end else begin
                        clk_count <= 16'd0;
                        if (rx_sync[1] == 1'b1) begin
                            data_out   <= rx_shift_reg;
                            data_ready <= 1'b1;
                        end
                        state <= STATE_IDLE;
                    end
                end

                default: begin
                    state <= STATE_IDLE;
                end

            endcase
        end
    end





endmodule

uart/src/transmitter.v
module transmitter (
    input  wire       clk,
    input  wire       rst_n,
    input  wire [7:0] data_in,
    input  wire       tx_start,
    output reg        tx,
    output reg        busy
);

    parameter integer CLK_FREQ = 24_000_000;
    parameter integer BAUD_RATE = 115200;
    localparam integer CYC_PER_BIT = CLK_FREQ / BAUD_RATE;

    localparam [1:0] STATE_IDLE = 2'd0;
    localparam [1:0] STATE_START = 2'd1;
    localparam [1:0] STATE_DATA = 2'd2;
    localparam [1:0] STATE_STOP = 2'd3;

    reg [ 1:0] state;
    reg [ 2:0] bit_index;
    reg [15:0] clk_count;
    reg [ 7:0] tx_shift_reg;

    always @(posedge clk or negedge rst_n) begin
        if (!rst_n) begin
            state        <= STATE_IDLE;
            tx           <= 1'b1;  // Idle state of UART is high
            busy         <= 1'b0;
            bit_index    <= 3'd0;
            clk_count    <= 16'd0;
            tx_shift_reg <= 8'd0;
        end else begin
            case (state)
                STATE_IDLE: begin
                    tx        <= 1'b1;  // Idle state
                    busy      <= 1'b0;
                    bit_index <= 3'd0;
                    clk_count <= 16'd0;

                    if (tx_start) begin
                        tx_shift_reg <= data_in;
                        state        <= STATE_START;
                        busy         <= 1'b1;
                    end
                end
                STATE_START: begin
                    tx <= 1'b0;  // Start bit
                    if (clk_count < CYC_PER_BIT - 1) begin
                        clk_count <= clk_count + 1'b1;
                    end else begin
                        clk_count <= 16'd0;
                        state     <= STATE_DATA;
                    end
                end
                STATE_DATA: begin
                    tx <= tx_shift_reg[bit_index];  // Send LSB first
                    if (clk_count < CYC_PER_BIT - 1) begin
                        clk_count <= clk_count + 1'b1;
                    end else begin
                        clk_count <= 16'd0;
                        if (bit_index < 3'd7) begin
                            bit_index <= bit_index + 1'b1;
                        end else begin
                            bit_index <= 3'd0;
                            state     <= STATE_STOP;
                        end
                    end
                end
                STATE_STOP: begin
                    tx <= 1'b1;  // Stop bit
                    if (clk_count < CYC_PER_BIT - 1) begin
                        clk_count <= clk_count + 1'b1;
                    end else begin
                        clk_count <= 16'd0;
                        state     <= STATE_IDLE;
                        busy      <= 1'b0;
                    end
                end
                default: state <= STATE_IDLE;
            endcase
        end
    end

endmodule

uart/src/main.v
`include "receiver.v"
`include "transmitter.v"

module main (
    input  wire clk,
    input  wire rst_n,
    input  wire rx,
    output wire tx
);

    //Simple UART echo sample

    wire [7:0] data_buffer;
    wire       data_ready;
    wire       tx_busy;
    wire [7:0] tx_captured;
    wire       tx_captured_ready;


    receiver uart_receiver (
        .clk       (clk),
        .rst_n     (rst_n),
        .rx        (rx),
        .data_out  (data_buffer),
        .data_ready(data_ready)
    );


    transmitter uart_transmitter (
        .clk     (clk),
        .rst_n   (rst_n),
        .tx_start(data_ready),
        .data_in (data_buffer),
        .tx      (tx),
        .busy    (tx_busy)
    );

    // Monitor de TX - captura o que foi transmitido

    receiver tx_monitor (
        .clk       (clk),
        .rst_n     (rst_n),
        .rx        (tx),                // conecta ao TX!
        .data_out  (tx_captured),
        .data_ready(tx_captured_ready)
    );

    // Buffer de debug - armazena último byte capturado do TX
    reg [7:0] last_tx_captured;

    always @(posedge clk or negedge rst_n) begin
        if (!rst_n) last_tx_captured <= 8'd0;
        else if (tx_captured_ready) last_tx_captured <= tx_captured;
    end

endmodule

uart/src/tb_main.v
`timescale 1ns / 1ps
`include "main.v"

module tb_main;
    reg  clk;
    reg  rst_n;
    reg  rx;
    wire tx;

    main dut (
        .clk  (clk),
        .rst_n(rst_n),
        .rx   (rx),
        .tx   (tx)
    );


    localparam real CLK_FREQ = 24_000_000;  // 24 MHz
    localparam real CLK_PERIOD = 1e9 / CLK_FREQ;  // Clock period in nanoseconds

    initial clk = 0;
    always #(CLK_PERIOD / 2) clk = ~clk;  // Generate clock signal


    initial begin
        rst_n = 0;
        rx    = 1;  // Idle state of UART is high
        #(CLK_PERIOD * 5);  // Hold reset for a few clock cycles

        rst_n = 1;  // Release reset
    end

    localparam real BAUDRATE = 115200;
    localparam real BIT_PERIOD = 1e9 / BAUDRATE;  // Bit period in nanoseconds


    task send_byte(input [7:0] byte);
        integer i;
        begin
            // Start bit
            rx = 0;
            #(BIT_PERIOD);

            for (i = 0; i < 8; i = i + 1) begin
                rx = byte[i];  // Send LSB first
                #(BIT_PERIOD);
            end

            // Stop bit
            rx = 1;
            #(BIT_PERIOD);
        end
    endtask

    initial begin
        $dumpfile("tb_main.vcd");
        $dumpvars(0, tb_main);

        #(BIT_PERIOD * 2);  // Wait for the system to stabilize
        send_byte(8'h55);  // Send a test byte (0x55)
        #(BIT_PERIOD * (1+8+1) * 2);  // Wait for the byte to be processed
        send_byte(8'hAA);  // Send another test byte (0xAA)
        #(BIT_PERIOD * (1+8+1) * 2);  // Wait for the byte to be processed
        $finish;  // End the simulation
    end


endmodule

uart/src/tb_main.vcd
$date
	Mon Feb 16 18:22:13 2026
$end
$version
	Icarus Verilog
$end
$timescale
	1ps
$end
$scope module tb_main $end
$var wire 1 ! tx $end
$var real 1 " BAUDRATE $end
$var real 1 # BIT_PERIOD $end
$var real 1 $ CLK_FREQ $end
$var real 1 % CLK_PERIOD $end
$var reg 1 & clk $end
$var reg 1 ' rst_n $end
$var reg 1 ( rx $end
$scope module dut $end
$var wire 1 & clk $end
$var wire 1 ' rst_n $end
$var wire 1 ( rx $end
$var wire 1 ) tx_captured_ready $end
$var wire 8 * tx_captured [7:0] $end
$var wire 1 + tx_busy $end
$var wire 1 ! tx $end
$var wire 1 , data_ready $end
$var wire 8 - data_buffer [7:0] $end
$var reg 8 . last_tx_captured [7:0] $end
$scope module tx_monitor $end
$var wire 1 & clk $end
$var wire 1 ' rst_n $end
$var wire 1 ! rx $end
$var parameter 32 / BAUD_RATE $end
$var parameter 32 0 CLK_FREQ $end
$var parameter 32 1 CYC_PER_BIT $end
$var parameter 32 2 HALF_CYC_PER_BIT $end
$var parameter 2 3 STATE_DATA $end
$var parameter 2 4 STATE_IDLE $end
$var parameter 2 5 STATE_START $end
$var parameter 2 6 STATE_STOP $end
$var reg 3 7 bit_index [2:0] $end
$var reg 16 8 clk_count [15:0] $end
$var reg 8 9 data_out [7:0] $end
$var reg 1 ) data_ready $end
$var reg 8 : rx_shift_reg [7:0] $end
$var reg 2 ; rx_sync [1:0] $end
$var reg 2 < state [1:0] $end
$upscope $end
$scope module uart_receiver $end
$var wire 1 & clk $end
$var wire 1 ' rst_n $end
$var wire 1 ( rx $end
$var parameter 32 = BAUD_RATE $end
$var parameter 32 > CLK_FREQ $end
$var parameter 32 ? CYC_PER_BIT $end
$var parameter 32 @ HALF_CYC_PER_BIT $end
$var parameter 2 A STATE_DATA $end
$var parameter 2 B STATE_IDLE $end
$var parameter 2 C STATE_START $end
$var parameter 2 D STATE_STOP $end
$var reg 3 E bit_index [2:0] $end
$var reg 16 F clk_count [15:0] $end
$var reg 8 G data_out [7:0] $end
$var reg 1 , data_ready $end
$var reg 8 H rx_shift_reg [7:0] $end
$var reg 2 I rx_sync [1:0] $end
$var reg 2 J state [1:0] $end
$upscope $end
$scope module uart_transmitter $end
$var wire 1 & clk $end
$var wire 8 K data_in [7:0] $end
$var wire 1 ' rst_n $end
$var wire 1 , tx_start $end
$var parameter 32 L BAUD_RATE $end
$var parameter 32 M CLK_FREQ $end
$var parameter 32 N CYC_PER_BIT $end
$var parameter 2 O STATE_DATA $end
$var parameter 2 P STATE_IDLE $end
$var parameter 2 Q STATE_START $end
$var parameter 2 R STATE_STOP $end
$var reg 3 S bit_index [2:0] $end
$var reg 1 + busy $end
$var reg 16 T clk_count [15:0] $end
$var reg 2 U state [1:0] $end
$var reg 1 ! tx $end
$var reg 8 V tx_shift_reg [7:0] $end
$upscope $end
$upscope $end
$scope task send_byte $end
$var reg 8 W byte [7:0] $end
$var integer 32 X i [31:0] $end
$upscope $end
$upscope $end
$enddefinitions $end
$comment Show the parameter values. $end
$dumpall
b11 R
b1 Q
b0 P
b10 O
b11010000 N
b1011011100011011000000000 M
b11100001000000000 L
b11 D
b1 C
b0 B
b10 A
b1101000 @
b11010000 ?
b1011011100011011000000000 >
b11100001000000000 =
b11 6
b1 5
b0 4
b10 3
b1101000 2
b11010000 1
b1011011100011011000000000 0
b11100001000000000 /
r41.66666666666666 %
r24000000 $
r8680.555555555555 #
r115200 "
$end
#0
$dumpvars
bx X
bx W
b0 V
b0 U
b0 T
b0 S
b0 K
b0 J
b11 I
b0 H
b0 G
b0 F
b0 E
b0 <
b11 ;
b0 :
b0 9
b0 8
b0 7
b0 .
b0 -
0,
0+
b0 *
0)
1(
0'
0&
1!
$end
#20833
1&
#41666
0&
#62499
1&
#83332
0&
#104165
1&
#124998
0&
#145831
1&
#166664
0&
#187497
1&
#208330
0&
#208333
1'
#229163
1&
#249996
0&
#270829
1&
#291662
0&
#312495
1&
#333328
0&
#354161
1&
#374994
0&
#395827
1&
#416660
0&
#437493
1&
#458326
0&
#479159
1&
#499992
0&
#520825
1&
#541658
0&
#562491
1&
#583324
0&
#604157
1&
#624990
0&
#645823
1&
#666656
0&
#687489
1&
#708322
0&
#729155
1&
#749988
0&
#770821
1&
#791654
0&
#812487
1&
#833320
0&
#854153
1&
#874986
0&
#895819
1&
#916652
0&
#937485
1&
#958318
0&
#979151
1&
#999984
0&
#1020817
1&
#1041650
0&
#1062483
1&
#1083316
0&
#1104149
1&
#1124982
0&
#1145815
1&
#1166648
0&
#1187481
1&
#1208314
0&
#1229147
1&
#1249980
0&
#1270813
1&
#1291646
0&
#1312479
1&
#1333312
0&
#1354145
1&
#1374978
0&
#1395811
1&
#1416644
0&
#1437477
1&
#1458310
0&
#1479143
1&
#1499976
0&
#1520809
1&
#1541642
0&
#1562475
1&
#1583308
0&
#1604141
1&
#1624974
0&
#1645807
1&
#1666640
0&
#1687473
1&
#1708306
0&
#1729139
1&
#1749972
0&
#1770805
1&
#1791638
0&
#1812471
1&
#1833304
0&
#1854137
1&
#1874970
0&
#1895803
1&
#1916636
0&
#1937469
1&
#1958302
0&
#1979135
1&
#1999968
0&
#2020801
1&
#2041634
0&
#2062467
1&
#2083300
0&
#2104133
1&
#2124966
0&
#2145799
1&
#2166632
0&
#2187465
1&
#2208298
0&
#2229131
1&
#2249964
0&
#2270797
1&
#2291630
0&
#2312463
1&
#2333296
0&
#2354129
1&
#2374962
0&
#2395795
1&
#2416628
0&
#2437461
1&
#2458294
0&
#2479127
1&
#2499960
0&
#2520793
1&
#2541626
0&
#2562459
1&
#2583292
0&
#2604125
1&
#2624958
0&
#2645791
1&
#2666624
0&
#2687457
1&
#2708290
0&
#2729123
1&
#2749956
0&
#2770789
1&
#2791622
0&
#2812455
1&
#2833288
0&
#2854121
1&
#2874954
0&
#2895787
1&
#2916620
0&
#2937453
1&
#2958286
0&
#2979119
1&
#2999952
0&
#3020785
1&
#3041618
0&
#3062451
1&
#3083284
0&
#3104117
1&
#3124950
0&
#3145783
1&
#3166616
0&
#3187449
1&
#3208282
0&
#3229115
1&
#3249948
0&
#3270781
1&
#3291614
0&
#3312447
1&
#3333280
0&
#3354113
1&
#3374946
0&
#3395779
1&
#3416612
0&
#3437445
1&
#3458278
0&
#3479111
1&
#3499944
0&
#3520777
1&
#3541610
0&
#3562443
1&
#3583276
0&
#3604109
1&
#3624942
0&
#3645775
1&
#3666608
0&
#3687441
1&
#3708274
0&
#3729107
1&
#3749940
0&
#3770773
1&
#3791606
0&
#3812439
1&
#3833272
0&
#3854105
1&
#3874938
0&
#3895771
1&
#3916604
0&
#3937437
1&
#3958270
0&
#3979103
1&
#3999936
0&
#4020769
1&
#4041602
0&
#4062435
1&
#4083268
0&
#4104101
1&
#4124934
0&
#4145767
1&
#4166600
0&
#4187433
1&
#4208266
0&
#4229099
1&
#4249932
0&
#4270765
1&
#4291598
0&
#4312431
1&
#4333264
0&
#4354097
1&
#4374930
0&
#4395763
1&
#4416596
0&
#4437429
1&
#4458262
0&
#4479095
1&
#4499928
0&
#4520761
1&
#4541594
0&
#4562427
1&
#4583260
0&
#4604093
1&
#4624926
0&
#4645759
1&
#4666592
0&
#4687425
1&
#4708258
0&
#4729091
1&
#4749924
0&
#4770757
1&
#4791590
0&
#4812423
1&
#4833256
0&
#4854089
1&
#4874922
0&
#4895755
1&
#4916588
0&
#4937421
1&
#4958254
0&
#4979087
1&
#4999920
0&
#5020753
1&
#5041586
0&
#5062419
1&
#5083252
0&
#5104085
1&
#5124918
0&
#5145751
1&
#5166584
0&
#5187417
1&
#5208250
0&
#5229083
1&
#5249916
0&
#5270749
1&
#5291582
0&
#5312415
1&
#5333248
0&
#5354081
1&
#5374914
0&
#5395747
1&
#5416580
0&
#5437413
1&
#5458246
0&
#5479079
1&
#5499912
0&
#5520745
1&
#5541578
0&
#5562411
1&
#5583244
0&
#5604077
1&
#5624910
0&
#5645743
1&
#5666576
0&
#5687409
1&
#5708242
0&
#5729075
1&
#5749908
0&
#5770741
1&
#5791574
0&
#5812407
1&
#5833240
0&
#5854073
1&
#5874906
0&
#5895739
1&
#5916572
0&
#5937405
1&
#5958238
0&
#5979071
1&
#5999904
0&
#6020737
1&
#6041570
0&
#6062403
1&
#6083236
0&
#6104069
1&
#6124902
0&
#6145735
1&
#6166568
0&
#6187401
1&
#6208234
0&
#6229067
1&
#6249900
0&
#6270733
1&
#6291566
0&
#6312399
1&
#6333232
0&
#6354065
1&
#6374898
0&
#6395731
1&
#6416564
0&
#6437397
1&
#6458230
0&
#6479063
1&
#6499896
0&
#6520729
1&
#6541562
0&
#6562395
1&
#6583228
0&
#6604061
1&
#6624894
0&
#6645727
1&
#6666560
0&
#6687393
1&
#6708226
0&
#6729059
1&
#6749892
0&
#6770725
1&
#6791558
0&
#6812391
1&
#6833224
0&
#6854057
1&
#6874890
0&
#6895723
1&
#6916556
0&
#6937389
1&
#6958222
0&
#6979055
1&
#6999888
0&
#7020721
1&
#7041554
0&
#7062387
1&
#7083220
0&
#7104053
1&
#7124886
0&
#7145719
1&
#7166552
0&
#7187385
1&
#7208218
0&
#7229051
1&
#7249884
0&
#7270717
1&
#7291550
0&
#7312383
1&
#7333216
0&
#7354049
1&
#7374882
0&
#7395715
1&
#7416548
0&
#7437381
1&
#7458214
0&
#7479047
1&
#7499880
0&
#7520713
1&
#7541546
0&
#7562379
1&
#7583212
0&
#7604045
1&
#7624878
0&
#7645711
1&
#7666544
0&
#7687377
1&
#7708210
0&
#7729043
1&
#7749876
0&
#7770709
1&
#7791542
0&
#7812375
1&
#7833208
0&
#7854041
1&
#7874874
0&
#7895707
1&
#7916540
0&
#7937373
1&
#7958206
0&
#7979039
1&
#7999872
0&
#8020705
1&
#8041538
0&
#8062371
1&
#8083204
0&
#8104037
1&
#8124870
0&
#8145703
1&
#8166536
0&
#8187369
1&
#8208202
0&
#8229035
1&
#8249868
0&
#8270701
1&
#8291534
0&
#8312367
1&
#8333200
0&
#8354033
1&
#8374866
0&
#8395699
1&
#8416532
0&
#8437365
1&
#8458198
0&
#8479031
1&
#8499864
0&
#8520697
1&
#8541530
0&
#8562363
1&
#8583196
0&
#8604029
1&
#8624862
0&
#8645695
1&
#8666528
0&
#8687361
1&
#8708194
0&
#8729027
1&
#8749860
0&
#8770693
1&
#8791526
0&
#8812359
1&
#8833192
0&
#8854025
1&
#8874858
0&
#8895691
1&
#8916524
0&
#8937357
1&
#8958190
0&
#8979023
1&
#8999856
0&
#9020689
1&
#9041522
0&
#9062355
1&
#9083188
0&
#9104021
1&
#9124854
0&
#9145687
1&
#9166520
0&
#9187353
1&
#9208186
0&
#9229019
1&
#9249852
0&
#9270685
1&
#9291518
0&
#9312351
1&
#9333184
0&
#9354017
1&
#9374850
0&
#9395683
1&
#9416516
0&
#9437349
1&
#9458182
0&
#9479015
1&
#9499848
0&
#9520681
1&
#9541514
0&
#9562347
1&
#9583180
0&
#9604013
1&
#9624846
0&
#9645679
1&
#9666512
0&
#9687345
1&
#9708178
0&
#9729011
1&
#9749844
0&
#9770677
1&
#9791510
0&
#9812343
1&
#9833176
0&
#9854009
1&
#9874842
0&
#9895675
1&
#9916508
0&
#9937341
1&
#9958174
0&
#9979007
1&
#9999840
0&
#10020673
1&
#10041506
0&
#10062339
1&
#10083172
0&
#10104005
1&
#10124838
0&
#10145671
1&
#10166504
0&
#10187337
1&
#10208170
0&
#10229003
1&
#10249836
0&
#10270669
1&
#10291502
0&
#10312335
1&
#10333168
0&
#10354001
1&
#10374834
0&
#10395667
1&
#10416500
0&
#10437333
1&
#10458166
0&
#10478999
1&
#10499832
0&
#10520665
1&
#10541498
0&
#10562331
1&
#10583164
0&
#10603997
1&
#10624830
0&
#10645663
1&
#10666496
0&
#10687329
1&
#10708162
0&
#10728995
1&
#10749828
0&
#10770661
1&
#10791494
0&
#10812327
1&
#10833160
0&
#10853993
1&
#10874826
0&
#10895659
1&
#10916492
0&
#10937325
1&
#10958158
0&
#10978991
1&
#10999824
0&
#11020657
1&
#11041490
0&
#11062323
1&
#11083156
0&
#11103989
1&
#11124822
0&
#11145655
1&
#11166488
0&
#11187321
1&
#11208154
0&
#11228987
1&
#11249820
0&
#11270653
1&
#11291486
0&
#11312319
1&
#11333152
0&
#11353985
1&
#11374818
0&
#11395651
1&
#11416484
0&
#11437317
1&
#11458150
0&
#11478983
1&
#11499816
0&
#11520649
1&
#11541482
0&
#11562315
1&
#11583148
0&
#11603981
1&
#11624814
0&
#11645647
1&
#11666480
0&
#11687313
1&
#11708146
0&
#11728979
1&
#11749812
0&
#11770645
1&
#11791478
0&
#11812311
1&
#11833144
0&
#11853977
1&
#11874810
0&
#11895643
1&
#11916476
0&
#11937309
1&
#11958142
0&
#11978975
1&
#11999808
0&
#12020641
1&
#12041474
0&
#12062307
1&
#12083140
0&
#12103973
1&
#12124806
0&
#12145639
1&
#12166472
0&
#12187305
1&
#12208138
0&
#12228971
1&
#12249804
0&
#12270637
1&
#12291470
0&
#12312303
1&
#12333136
0&
#12353969
1&
#12374802
0&
#12395635
1&
#12416468
0&
#12437301
1&
#12458134
0&
#12478967
1&
#12499800
0&
#12520633
1&
#12541466
0&
#12562299
1&
#12583132
0&
#12603965
1&
#12624798
0&
#12645631
1&
#12666464
0&
#12687297
1&
#12708130
0&
#12728963
1&
#12749796
0&
#12770629
1&
#12791462
0&
#12812295
1&
#12833128
0&
#12853961
1&
#12874794
0&
#12895627
1&
#12916460
0&
#12937293
1&
#12958126
0&
#12978959
1&
#12999792
0&
#13020625
1&
#13041458
0&
#13062291
1&
#13083124
0&
#13103957
1&
#13124790
0&
#13145623
1&
#13166456
0&
#13187289
1&
#13208122
0&
#13228955
1&
#13249788
0&
#13270621
1&
#13291454
0&
#13312287
1&
#13333120
0&
#13353953
1&
#13374786
0&
#13395619
1&
#13416452
0&
#13437285
1&
#13458118
0&
#13478951
1&
#13499784
0&
#13520617
1&
#13541450
0&
#13562283
1&
#13583116
0&
#13603949
1&
#13624782
0&
#13645615
1&
#13666448
0&
#13687281
1&
#13708114
0&
#13728947
1&
#13749780
0&
#13770613
1&
#13791446
0&
#13812279
1&
#13833112
0&
#13853945
1&
#13874778
0&
#13895611
1&
#13916444
0&
#13937277
1&
#13958110
0&
#13978943
1&
#13999776
0&
#14020609
1&
#14041442
0&
#14062275
1&
#14083108
0&
#14103941
1&
#14124774
0&
#14145607
1&
#14166440
0&
#14187273
1&
#14208106
0&
#14228939
1&
#14249772
0&
#14270605
1&
#14291438
0&
#14312271
1&
#14333104
0&
#14353937
1&
#14374770
0&
#14395603
1&
#14416436
0&
#14437269
1&
#14458102
0&
#14478935
1&
#14499768
0&
#14520601
1&
#14541434
0&
#14562267
1&
#14583100
0&
#14603933
1&
#14624766
0&
#14645599
1&
#14666432
0&
#14687265
1&
#14708098
0&
#14728931
1&
#14749764
0&
#14770597
1&
#14791430
0&
#14812263
1&
#14833096
0&
#14853929
1&
#14874762
0&
#14895595
1&
#14916428
0&
#14937261
1&
#14958094
0&
#14978927
1&
#14999760
0&
#15020593
1&
#15041426
0&
#15062259
1&
#15083092
0&
#15103925
1&
#15124758
0&
#15145591
1&
#15166424
0&
#15187257
1&
#15208090
0&
#15228923
1&
#15249756
0&
#15270589
1&
#15291422
0&
#15312255
1&
#15333088
0&
#15353921
1&
#15374754
0&
#15395587
1&
#15416420
0&
#15437253
1&
#15458086
0&
#15478919
1&
#15499752
0&
#15520585
1&
#15541418
0&
#15562251
1&
#15583084
0&
#15603917
1&
#15624750
0&
#15645583
1&
#15666416
0&
#15687249
1&
#15708082
0&
#15728915
1&
#15749748
0&
#15770581
1&
#15791414
0&
#15812247
1&
#15833080
0&
#15853913
1&
#15874746
0&
#15895579
1&
#15916412
0&
#15937245
1&
#15958078
0&
#15978911
1&
#15999744
0&
#16020577
1&
#16041410
0&
#16062243
1&
#16083076
0&
#16103909
1&
#16124742
0&
#16145575
1&
#16166408
0&
#16187241
1&
#16208074
0&
#16228907
1&
#16249740
0&
#16270573
1&
#16291406
0&
#16312239
1&
#16333072
0&
#16353905
1&
#16374738
0&
#16395571
1&
#16416404
0&
#16437237
1&
#16458070
0&
#16478903
1&
#16499736
0&
#16520569
1&
#16541402
0&
#16562235
1&
#16583068
0&
#16603901
1&
#16624734
0&
#16645567
1&
#16666400
0&
#16687233
1&
#16708066
0&
#16728899
1&
#16749732
0&
#16770565
1&
#16791398
0&
#16812231
1&
#16833064
0&
#16853897
1&
#16874730
0&
#16895563
1&
#16916396
0&
#16937229
1&
#16958062
0&
#16978895
1&
#16999728
0&
#17020561
1&
#17041394
0&
#17062227
1&
#17083060
0&
#17103893
1&
#17124726
0&
#17145559
1&
#17166392
0&
#17187225
1&
#17208058
0&
#17228891
1&
#17249724
0&
#17270557
1&
#17291390
0&
#17312223
1&
#17333056
0&
#17353889
1&
#17361111
0(
b1010101 W
#17374722
0&
#17395555
b10 I
1&
#17416388
0&
#17437221
b0 I
1&
#17458054
0&
#17478887
b1 J
1&
#17499720
0&
#17520553
b1 F
1&
#17541386
0&
#17562219
b10 F
1&
#17583052
0&
#17603885
b11 F
1&
#17624718
0&
#17645551
b100 F
1&
#17666384
0&
#17687217
b101 F
1&
#17708050
0&
#17728883
b110 F
1&
#17749716
0&
#17770549
b111 F
1&
#17791382
0&
#17812215
b1000 F
1&
#17833048
0&
#17853881
b1001 F
1&
#17874714
0&
#17895547
b1010 F
1&
#17916380
0&
#17937213
b1011 F
1&
#17958046
0&
#17978879
b1100 F
1&
#17999712
0&
#18020545
b1101 F
1&
#18041378
0&
#18062211
b1110 F
1&
#18083044
0&
#18103877
b1111 F
1&
#18124710
0&
#18145543
b10000 F
1&
#18166376
0&
#18187209
b10001 F
1&
#18208042
0&
#18228875
b10010 F
1&
#18249708
0&
#18270541
b10011 F
1&
#18291374
0&
#18312207
b10100 F
1&
#18333040
0&
#18353873
b10101 F
1&
#18374706
0&
#18395539
b10110 F
1&
#18416372
0&
#18437205
b10111 F
1&
#18458038
0&
#18478871
b11000 F
1&
#18499704
0&
#18520537
b11001 F
1&
#18541370
0&
#18562203
b11010 F
1&
#18583036
0&
#18603869
b11011 F
1&
#18624702
0&
#18645535
b11100 F
1&
#18666368
0&
#18687201
b11101 F
1&
#18708034
0&
#18728867
b11110 F
1&
#18749700
0&
#18770533
b11111 F
1&
#18791366
0&
#18812199
b100000 F
1&
#18833032
0&
#18853865
b100001 F
1&
#18874698
0&
#18895531
b100010 F
1&
#18916364
0&
#18937197
b100011 F
1&
#18958030
0&
#18978863
b100100 F
1&
#18999696
0&
#19020529
b100101 F
1&
#19041362
0&
#19062195
b100110 F
1&
#19083028
0&
#19103861
b100111 F
1&
#19124694
0&
#19145527
b101000 F
1&
#19166360
0&
#19187193
b101001 F
1&
#19208026
0&
#19228859
b101010 F
1&
#19249692
0&
#19270525
b101011 F
1&
#19291358
0&
#19312191
b101100 F
1&
#19333024
0&
#19353857
b101101 F
1&
#19374690
0&
#19395523
b101110 F
1&
#19416356
0&
#19437189
b101111 F
1&
#19458022
0&
#19478855
b110000 F
1&
#19499688
0&
#19520521
b110001 F
1&
#19541354
0&
#19562187
b110010 F
1&
#19583020
0&
#19603853
b110011 F
1&
#19624686
0&
#19645519
b110100 F
1&
#19666352
0&
#19687185
b110101 F
1&
#19708018
0&
#19728851
b110110 F
1&
#19749684
0&
#19770517
b110111 F
1&
#19791350
0&
#19812183
b111000 F
1&
#19833016
0&
#19853849
b111001 F
1&
#19874682
0&
#19895515
b111010 F
1&
#19916348
0&
#19937181
b111011 F
1&
#19958014
0&
#19978847
b111100 F
1&
#19999680
0&
#20020513
b111101 F
1&
#20041346
0&
#20062179
b111110 F
1&
#20083012
0&
#20103845
b111111 F
1&
#20124678
0&
#20145511
b1000000 F
1&
#20166344
0&
#20187177
b1000001 F
1&
#20208010
0&
#20228843
b1000010 F
1&
#20249676
0&
#20270509
b1000011 F
1&
#20291342
0&
#20312175
b1000100 F
1&
#20333008
0&
#20353841
b1000101 F
1&
#20374674
0&
#20395507
b1000110 F
1&
#20416340
0&
#20437173
b1000111 F
1&
#20458006
0&
#20478839
b1001000 F
1&
#20499672
0&
#20520505
b1001001 F
1&
#20541338
0&
#20562171
b1001010 F
1&
#20583004
0&
#20603837
b1001011 F
1&
#20624670
0&
#20645503
b1001100 F
1&
#20666336
0&
#20687169
b1001101 F
1&
#20708002
0&
#20728835
b1001110 F
1&
#20749668
0&
#20770501
b1001111 F
1&
#20791334
0&
#20812167
b1010000 F
1&
#20833000
0&
#20853833
b1010001 F
1&
#20874666
0&
#20895499
b1010010 F
1&
#20916332
0&
#20937165
b1010011 F
1&
#20957998
0&
#20978831
b1010100 F
1&
#20999664
0&
#21020497
b1010101 F
1&
#21041330
0&
#21062163
b1010110 F
1&
#21082996
0&
#21103829
b1010111 F
1&
#21124662
0&
#21145495
b1011000 F
1&
#21166328
0&
#21187161
b1011001 F
1&
#21207994
0&
#21228827
b1011010 F
1&
#21249660
0&
#21270493
b1011011 F
1&
#21291326
0&
#21312159
b1011100 F
1&
#21332992
0&
#21353825
b1011101 F
1&
#21374658
0&
#21395491
b1011110 F
1&
#21416324
0&
#21437157
b1011111 F
1&
#21457990
0&
#21478823
b1100000 F
1&
#21499656
0&
#21520489
b1100001 F
1&
#21541322
0&
#21562155
b1100010 F
1&
#21582988
0&
#21603821
b1100011 F
1&
#21624654
0&
#21645487
b1100100 F
1&
#21666320
0&
#21687153
b1100101 F
1&
#21707986
0&
#21728819
b1100110 F
1&
#21749652
0&
#21770485
b1100111 F
1&
#21791318
0&
#21812151
b10 J
b0 F
1&
#21832984
0&
#21853817
b1 F
1&
#21874650
0&
#21895483
b10 F
1&
#21916316
0&
#21937149
b11 F
1&
#21957982
0&
#21978815
b100 F
1&
#21999648
0&
#22020481
b101 F
1&
#22041314
0&
#22062147
b110 F
1&
#22082980
0&
#22103813
b111 F
1&
#22124646
0&
#22145479
b1000 F
1&
#22166312
0&
#22187145
b1001 F
1&
#22207978
0&
#22228811
b1010 F
1&
#22249644
0&
#22270477
b1011 F
1&
#22291310
0&
#22312143
b1100 F
1&
#22332976
0&
#22353809
b1101 F
1&
#22374642
0&
#22395475
b1110 F
1&
#22416308
0&
#22437141
b1111 F
1&
#22457974
0&
#22478807
b10000 F
1&
#22499640
0&
#22520473
b10001 F
1&
#22541306
0&
#22562139
b10010 F
1&
#22582972
0&
#22603805
b10011 F
1&
